{
	"variables": {
		"client_id": "{{ CLIENT_ID }}",
		"client_secret": "{{ CLIENT_SECRET }}",
		"tenant_id": "{{ TENANT_ID }}",
		"subscription_id": "{{ AZURE_SUBSCRIPTION_ID }}"
	},
	"builders": [{
		"type": "azure-arm",
		"managed_image_resource_group_name": "myPackerGroup",
                "managed_image_name": "myPackerImage",
		"os_type": "Linux",
		"image_publisher": "Canonical",
		"image_offer": "UbuntuServer",
		"image_sku": "18.04-LTS",

		"communicator": "winrm",
		"winrm_use_ssl": true,
		"winrm_insecure": true,
		"winrm_timeout": "5m",
		"winrm_username": "packer",

		"azure_tags": {
			"Service": "Web"
		},

		"build_resource_group_name": "myPackerGroup",
		"vm_size": "Standard_D2_v2"
	}],
	"provisioners": [{
		"inline": [
			"echo 'Hello, World!' > index.html",
			"nohup busybox httpd -f -p 80 &"
			],
			"inline_shebang": "/bin/sh -x",
			"type": "shell"
	}]
}
